bin2dec/__init__.py
bin2dec/bin2dec.py
bin2dec/convert.py
bin2dec-0.0.0.1.dist-info/METADATA
bin2dec-0.0.0.1.dist-info/WHEEL
bin2dec-0.0.0.1.dist-info/top_level.txt
bin2dec-0.0.0.1.dist-info/RECORD
